layker/__about__.py
layker/__init__.py
layker/__main__.py
layker/differences.py
layker/loader.py
layker/logger.py
layker/main.py
layker/snapshot_table.py
layker/snapshot_yaml.py
layker/resources/example.yaml
layker/resources/layker_audit.yaml
layker/resources/layker_test.yaml
layker/utils/__init__.py
layker/utils/color.py
layker/utils/dry_run.py
layker/utils/paths.py
layker/utils/printer.py
layker/utils/spark.py
layker/utils/table.py
layker/utils/timer.py
layker/utils/yaml_table_dump.py
layker/validators/__init__.py
layker/validators/differences.py
layker/validators/params.py
layker-0.1.0.dist-info/licenses/LICENSE
layker-0.1.0.dist-info/METADATA
layker-0.1.0.dist-info/WHEEL
layker-0.1.0.dist-info/entry_points.txt
layker-0.1.0.dist-info/top_level.txt
layker-0.1.0.dist-info/RECORD
