Metadata-Version: 2.4
Name: layker
Version: 0.1.0
Summary: Lakehouse-Aligned YAML Kit for Engineering Rules
Author-email: Levi Gagne <levigagne0@gmail.com>
License: L.M.G. SERVICES GROUP LICENSE  
Project-URL: Homepage, https://github.com/Levi-Gagne/layker
Project-URL: Issues, https://github.com/Levi-Gagne/layker/issues
Project-URL: Documentation, https://github.com/Levi-Gagne/layker#readme
Project-URL: Source, https://github.com/Levi-Gagne/layker
Keywords: databricks,delta,delta-lake,spark,schema,ddl,yaml,audit
Classifier: Development Status :: 3 - Alpha
Classifier: Environment :: Other Environment
Classifier: Framework :: Pytest
Classifier: Intended Audience :: Developers
Classifier: Intended Audience :: Information Technology
Classifier: License :: Other/Proprietary License
Classifier: Operating System :: OS Independent
Classifier: Programming Language :: Python
Classifier: Programming Language :: Python :: 3
Classifier: Programming Language :: Python :: 3.8
Classifier: Programming Language :: Python :: 3.9
Classifier: Programming Language :: Python :: 3.10
Classifier: Programming Language :: Python :: 3.11
Classifier: Topic :: Database
Classifier: Topic :: Software Development :: Build Tools
Classifier: Topic :: Utilities
Requires-Python: >=3.8
License-File: LICENSE
Requires-Dist: pyspark>=3.3.0
Requires-Dist: pyyaml>=5.4
Requires-Dist: typing-extensions>=4.0
Provides-Extra: dev
Requires-Dist: pytest>=7.0; extra == "dev"
Requires-Dist: black>=24.0; extra == "dev"
Requires-Dist: ruff>=0.4.0; extra == "dev"
Requires-Dist: mypy>=1.5.0; extra == "dev"
Dynamic: license-file
